CHANGES.rst
LICENSE.txt
MANIFEST.in
README.rst
setup.cfg
setup.py
bin/shellstreaming
shellstreaming/__init__.py
shellstreaming.egg-info/PKG-INFO
shellstreaming.egg-info/SOURCES.txt
shellstreaming.egg-info/dependency_links.txt
shellstreaming.egg-info/requires.txt
shellstreaming.egg-info/top_level.txt
shellstreaming/api/__init__.py
shellstreaming/autodeploy/__init__.py
shellstreaming/autodeploy/auto_deploy.py
shellstreaming/config/__init__.py
shellstreaming/config/parse.py
shellstreaming/core/__init__.py
shellstreaming/core/base_job.py
shellstreaming/core/batch.py
shellstreaming/core/batch_queue.py
shellstreaming/core/partitioned_batch_queue.py
shellstreaming/core/queue_group.py
shellstreaming/core/remote_queue.py
shellstreaming/istream/__init__.py
shellstreaming/istream/base.py
shellstreaming/istream/incint.py
shellstreaming/istream/randint.py
shellstreaming/istream/randsentence.py
shellstreaming/istream/rotatesentence.py
shellstreaming/istream/stdin.py
shellstreaming/istream/textfile.py
shellstreaming/istream/textfile_tail.py
shellstreaming/istream/tweet.py
shellstreaming/jobgraph/__init__.py
shellstreaming/master/__init__.py
shellstreaming/master/job_placement.py
shellstreaming/master/master.py
shellstreaming/master/master_struct.py
shellstreaming/operator/__init__.py
shellstreaming/operator/base.py
shellstreaming/operator/copy_split.py
shellstreaming/operator/count_window.py
shellstreaming/operator/external_time_window.py
shellstreaming/operator/filter_split.py
shellstreaming/operator/loop.py
shellstreaming/operator/shell_cmd.py
shellstreaming/operator/sort.py
shellstreaming/ostream/__init__.py
shellstreaming/ostream/base.py
shellstreaming/ostream/io_stream.py
shellstreaming/ostream/localfile.py
shellstreaming/ostream/null.py
shellstreaming/ostream/stdout.py
shellstreaming/scheduler/__init__.py
shellstreaming/scheduler/master_main.py
shellstreaming/scheduler/master_sched_allworker.py
shellstreaming/scheduler/master_sched_firstworker.py
shellstreaming/scheduler/master_sched_randomworker.py
shellstreaming/scheduler/worker_main.py
shellstreaming/scheduler/worker_sched_single_thread.py
