Metadata-Version: 1.1
Name: shellstreaming
Version: 0.1.1
Summary: A stream processor working with shell commands
Home-page: https://github.com/laysakura/shellstreaming
Author: Sho Nakatani
Author-email: lay.sakura@gmail.com
License: LICENSE.txt
Platform: UNKNOWN
Classifier: Programming Language :: Python
Classifier: Development Status :: 4 - Beta
Classifier: License :: OSI Approved :: Apache Software License
Classifier: Programming Language :: Python :: 2.7
Classifier: Operating System :: POSIX :: Linux
